{
  "users": [
    {
      "id": 19,
      "Name": "Priya",
      "Role": "1",
      "Email": "priya11@gmail.com",
      "Contact": "2345678912",
      "Password": "Test1234"
    },
    {
      "id": 22,
      "Email": "Aman@gmail.com",
      "Name": "Aman",
      "Contact": "3425627282",
      "Role": "0",
      "Password": "Test"
    },
    {
      "id": 24,
      "Name": "Payal",
      "Role": "0",
      "Email": "Payal@gmail.com",
      "Contact": "5245621362",
      "Password": "Test"
    },
    {
      "id": 26,
      "Name": "fvvegfv",
      "Password": "efbehw",
      "Email": "nbdnc",
      "Contact": "2563462537",
      "Role": "0"
    },
    {
      "id": 28,
      "Name": "Pramedha",
      "Password": "Test1234",
      "Email": "Pramedha@gmail.com",
      "Contact": "24324345345345",
      "Role": "0"
    },
    {
      "id": 29,
      "Name": "Radhe12",
      "Password": "Test123",
      "Email": "Radhe@gmail.com",
      "Contact": "5245252626",
      "Role": "0"
    },
    {
      "id": 30,
      "Name": "RitaSethi",
      "Password": "Test@123",
      "Email": "Rita@gmail.com",
      "Contact": "1324252627",
      "Role": "0"
    },
    {
      "id": 34,
      "Name": "Amanpreet",
      "Password": "Test@123",
      "Email": "Amanpreet@gmail.com",
      "Contact": "4316528791",
      "Role": ""
    },
    {
      "id": 35,
      "Name": "Ganesh",
      "Password": "Test1234",
      "Email": "Ganesh@gmail.com",
      "Contact": "1525238477",
      "Role": "0"
    },
    {
      "id": 36,
      "Name": "Chanchal",
      "Email": "Chanchal@gmail.com",
      "Contact": "3425167854",
      "Role": "1",
      "Password": "Test1234"
    }
  ]
}